eolab/georastertools/__init__.py
eolab/georastertools/filtering.py
eolab/georastertools/georastertools.py
eolab/georastertools/hillshade.py
eolab/georastertools/main.py
eolab/georastertools/radioindice.py
eolab/georastertools/speed.py
eolab/georastertools/svf.py
eolab/georastertools/tiling.py
eolab/georastertools/timeseries.py
eolab/georastertools/utils.py
eolab/georastertools/zonalstats.py
eolab/georastertools/cli/__init__.py
eolab/georastertools/cli/filtering.py
eolab/georastertools/cli/hillshade.py
eolab/georastertools/cli/radioindice.py
eolab/georastertools/cli/speed.py
eolab/georastertools/cli/svf.py
eolab/georastertools/cli/tiling.py
eolab/georastertools/cli/timeseries.py
eolab/georastertools/cli/utils_cli.py
eolab/georastertools/cli/zonalstats.py
eolab/georastertools/processing/__init__.py
eolab/georastertools/processing/algo.py
eolab/georastertools/processing/rasterproc.py
eolab/georastertools/processing/sliding.py
eolab/georastertools/processing/stats.py
eolab/georastertools/processing/vector.py
eolab/georastertools/product/__init__.py
eolab/georastertools/product/rasterproduct.py
eolab/georastertools/product/rastertype.py
eolab/georastertools/product/rastertypes.json
eolab/georastertools/product/vrt.py
georastertools-0.7.3.dist-info/licenses/AUTHORS.rst
georastertools-0.7.3.dist-info/licenses/LICENSE.txt
georastertools-0.7.3.dist-info/METADATA
georastertools-0.7.3.dist-info/WHEEL
georastertools-0.7.3.dist-info/entry_points.txt
georastertools-0.7.3.dist-info/top_level.txt
georastertools-0.7.3.dist-info/RECORD
