Metadata-Version: 2.4
Name: georastertools
Version: 0.7.3
Summary: Collection of tools for raster data
Home-page: https://github.com/CNES/rastertools
Author: Olivier Queyrut
Author-email: olivier.queyrut@cnes.fr
License: apache v2
Project-URL: Source, https://github.com/cnes/rastertools
Project-URL: Changelog, https://github.com/cnes/rastertools/blob/master/CHANGELOG.rst
Project-URL: Issues, https://github.com/cnes/rastertools/issues
Platform: any
Classifier: Development Status :: 5 - Production/Stable
Classifier: Programming Language :: Python
Requires-Python: >=3.8.13
License-File: LICENSE.txt
License-File: AUTHORS.rst
Requires-Dist: click==8.1.8
Requires-Dist: rasterio
Requires-Dist: pytest>=3.6
Requires-Dist: pytest-cov
Requires-Dist: geopandas==0.13
Requires-Dist: kiwisolver==1.4.5
Requires-Dist: matplotlib==3.7.3
Requires-Dist: packaging==24.1
Requires-Dist: fiona==1.9.6
Requires-Dist: sphinx_rtd_theme==3.0.1
Requires-Dist: pip==24.2
Requires-Dist: sphinx==7.1.2
Requires-Dist: scipy==1.16
Requires-Dist: pyscaffold
Requires-Dist: gdal==3.5.0
Requires-Dist: tqdm==4.66
Provides-Extra: testing
Requires-Dist: setuptools; extra == "testing"
Requires-Dist: pytest; extra == "testing"
Requires-Dist: pytest-cov; extra == "testing"
Dynamic: author
Dynamic: description
Dynamic: description-content-type
Dynamic: home-page
Dynamic: keywords
Dynamic: license-file
Dynamic: requires-dist
Dynamic: requires-python
Dynamic: summary
